{
	"executable": "ArcadeManager",
	"splashscreen": {
		"imageFile": "/wwwroot/img/splash.png"
	},
	"name": "ArcadeManager",
	"author": "cosmo0",
	"singleInstance": true,
	"build": {
		"appId": "com.ArcadeManager.app",
		"productName": "ArcadeManager",
		"copyright": "Copyright © 2021",
		"buildVersion": "6.1.0",
		"compression": "maximum",
		"win": {
			"target": [
				{
					"target": "nsis",
					"arch": [ "x64", "arm64" ]
				},
				{
					"target": "zip",
					"arch": [ "x64", "arm64" ]
				}
			],
			"icon": "bin/Assets/electron.ico"
		},
		"linux": {
			"target": [
				{
					"target": "AppImage",
					"arch": [ "x64", "arm64" ]
				},
				{
					"target": "snap",
					"arch": [ "x64", "arm64" ]
				},
				{
					"target": "zip",
					"arch": [ "x64", "arm64" ]
				}
			],
			"icon": "bin/Assets/electron_256x256.png"
		},
		"mac": {
			"target": [
				{
					"target": "dmg",
					"arch": [ "x64", "arm64" ]
				},
				{
					"target": "zip",
					"arch": [ "x64", "arm64" ]
				}
			],
			"icon": "bin/Assets/icon.icns",
			"category": "public.app-category.games"
		},
		"directories": {
			"output": "../../../bin/Desktop",
			"buildResources": "Assets"
		},
		"extraResources": [
			{
				"from": "./bin",
				"to": "bin",
				"filter": [ "**/*" ]
			}
		],
		"files": [
			{
				"from": "./ElectronHostHook/node_modules",
				"to": "ElectronHostHook/node_modules",
				"filter": [ "**/*" ]
			},
			"**/*"
		]
	}
}
